{"persona_id": "1564812d-5b76-4369-9980-10578c8bb0ed", "locale": "vi_VN", "timezone": "Asia/Ho_Chi_Minh", "name_full": "Nguyễn Hoàng Khải", "dob": "1962-12-31", "gender": "male", "nationality": "Viet Nam", "languages": [{"code": "vi", "level": "native"}, {"code": "en", "level": "advanced"}], "location_region": "65, Thôn Bình Kim, Xã 24, Quận Bảo Giang Quảng Bình", "appearance": {"height_cm": 188.0, "weight_kg": 89.3, "hair_color": "Blue", "eye_color": "Blue"}, "contacts": {"phone": "093-840-4581", "email": "bdanh@hong.com", "website": "lo.biz.vn", "username": "que81"}, "work_education": {"job_title": "Giám đốc vận hành", "employer": "Nguyễn-Lỡ Tập đoàn", "education": {"level": "Cử nhân", "university": "Đại học Kinh tế Quốc dân"}, "skills": ["Quản lý chuỗi cung ứng", "Hoạch định sản xuất", "Quản lý kho bãi", "Logistics", "Phân tích dữ liệu kinh doanh", "Quản lý dự án", "Tối ưu hóa quy trình", "Lãnh đạo đội nhóm", "Giải quyết vấn đề", "Đàm phán", "Quản lý ngân sách", "Chiến lược kinh doanh", "Kiểm soát chất lượng", "Quản lý rủi ro", "Hệ thống thông tin quản lý", "Kỹ năng giao tiếp", "Tư duy phản biện", "Thích ứng nhanh", "Quản lý hiệu suất", "Phát triển bền vững"], "salary_usd_per_year": 93100.0, "salary_vnd_per_month": 12122000, "usd_to_vnd_rate": 25000}, "personality": {"tone_style": ["nghiêm túc", "quyết đoán", "thực tế", "có trách nhiệm"], "values": ["kỷ luật", "hiệu quả", "trung thực", "gia đình", "phát triển bền vững"], "signature_phrases": ["Cần phải tối ưu hơn nữa.", "Hiệu quả là trên hết.", "Chúng ta hãy nhìn vào số liệu."]}, "preferences": {"music": ["Tình khúc vàng", "Nhạc tiền chiến", "Nhạc Trịnh Công Sơn", "Nhạc đỏ"], "movies": ["Ván bài lật ngửa", "Biệt động Sài Gòn", "Cánh đồng hoang", "Chuyện của Pao"], "food": ["Phở", "Bún chả", "Cơm tấm", "Bánh mì"], "sports": ["Cầu lông", "Bóng bàn", "Đi bộ", "Thái cực quyền"]}, "timeline": [{"time": "1962", "event_name": "Chào đời tại Quảng Bình"}, {"time": "1980", "event_name": "Tốt nghiệp cấp 3"}, {"time": "1980-1984", "event_name": "Học Cử nhân tại Đại học Kinh tế Quốc dân"}, {"time": "1984", "event_name": "Tốt nghiệp Đại học Kinh tế Quốc dân"}, {"time": "1984", "event_name": "Bắt đầu công việc đầu tiên tại một công ty logistics"}, {"time": "1995", "event_name": "Thăng chức lên vị trí Quản lý kho vận"}, {"time": "2005", "event_name": "Đảm nhiệm vị trí Trưởng phòng Vận hành"}, {"time": "2015", "event_name": "Trở thành Giám đốc vận hành tại Nguyễn-Lỡ Group"}, {"time": "2022", "event_name": "Nghỉ hưu và dành thời gian cho gia đình"}]}