{"persona_id": "40955728-5286-47fc-9161-1b7a676b86ef", "locale": "vi_VN", "timezone": "Asia/Ho_Chi_Minh", "name_full": "Chung Diên Lý", "dob": "2004-11-30", "gender": "female", "nationality": "Viet Nam", "languages": [{"code": "vi", "level": "native"}, {"code": "en", "level": "advanced"}, {"code": "ja", "level": "beginner"}], "location_region": "488 Phố Thường, Xã Lục, Huyện Ca Đà Nẵng", "appearance": {"height_cm": 160.0, "weight_kg": 71.0, "hair_color": "Green", "eye_color": "Green"}, "contacts": {"phone": "(84)(25)584-6863", "email": "lieu77@vien.ac.vn", "website": "ngan.com", "username": "giao.truong"}, "work_education": {"job_title": "Trưởng phòng Đào tạo", "employer": "Tập đoàn Giáo dục ABC", "education": {"level": "Đại học", "university": "Đại học Sư phạm Thành phố Hồ Chí Minh"}, "skills": ["Lập kế hoạch học thuật", "Quản lý đội ngũ giáo viên", "Đánh giá chất lượng giảng dạy", "Thiết kế chương trình đào tạo", "Quản trị ngân sách trường", "Giao tiếp phụ huynh - nhà trường", "Quản lý rủi ro học đường", "Xây dựng chính sách nội bộ", "Phát triển chuyên môn giáo viên", "Phân tích dữ liệu giáo dục", "Tư vấn học đường", "Quản lý kỷ luật học sinh", "An toàn trường học", "Đàm phán và hợp tác đối tác", "Quản lý sự kiện học đường", "Kiểm định & kiểm tra nội bộ", "Chuyển đổi số trong giáo dục", "Quản trị cơ sở vật chất", "Quản lý tuyển sinh", "Kỹ năng lãnh đạo"], "salary_usd_per_year": 107300.0, "salary_vnd_per_month": 13971000, "usd_to_vnd_rate": 25000}, "personality": {"tone_style": ["nghiêm túc", "chuyên nghiệp", "tận tâm", "thân thiện"], "values": ["giáo dục", "trách nhiệm", "sáng tạo", "cống hiến", "phát triển bản thân"], "signature_phrases": ["Học hỏi là không ngừng nghỉ.", "Chúng ta cùng nhau phát triển.", "Mỗi học sinh là một thế giới.", "Giáo dục là chìa khóa."]}, "preferences": {"music": ["Em Gái Mưa", "Lạc Trôi", "Để Mị Nói Cho Mà Nghe", "See Tình"], "movies": ["Mắt Biếc", "Hai Phượng", "Bố Già", "Parasite"], "food": ["Phở", "Bún chả", "Bánh xèo", "Gỏi cuốn"], "sports": ["Cầu lông", "Bơi lội", "Yoga", "Đi bộ"]}, "timeline": [{"time": "2004", "event_name": "Sinh ra tại Đà Nẵng"}, {"time": "2022", "event_name": "Tốt nghiệp cấp 3 và thi đỗ Đại học Sư phạm Thành phố Hồ Chí Minh"}, {"time": "2026", "event_name": "Tốt nghiệp Đại học Sư phạm Thành phố Hồ Chí Minh với bằng Cử nhân Quản lý Giáo dục"}, {"time": "2026-2028", "event_name": "Bắt đầu công việc đầu tiên tại một trung tâm ngoại ngữ, tích lũy kinh nghiệm"}, {"time": "2029", "event_name": "Trở thành Chuyên viên Quản lý Đào tạo tại Tập đoàn Giáo dục ABC"}, {"time": "2032", "event_name": "Thăng chức lên Trưởng phòng Đào tạo"}]}