{"persona_id": "471645d1-1e29-4155-aa71-9665adb12b9e", "locale": "vi_VN", "timezone": "Asia/Ho_Chi_Minh", "name_full": "Nguyễn Thào Thắng", "dob": "1984-5-31", "gender": "male", "nationality": "Viet Nam", "languages": [{"code": "vi", "level": "native"}, {"code": "en", "level": "advanced"}, {"code": "ja", "level": "beginner"}], "location_region": "338 Phố Bàng Quyền Sa, Xã Vĩnh Bình, Quận 71 Cần Thơ", "appearance": {"height_cm": 188.0, "weight_kg": 86.1, "hair_color": "Green", "eye_color": "Green"}, "contacts": {"phone": "(0218)479-1073", "email": "chuong.nhien@mau.net", "website": "ba.info", "username": "thong.vu"}, "work_education": {"job_title": "Trợ lý Nghiên cứu Khoa học Xã hội", "employer": "Tập đoàn Diệp", "education": {"level": "Cử nhân", "university": "Đại học Khoa học Xã hội và Nhân văn, Đại học Quốc gia TP.HCM"}, "skills": ["Lập kế hoạch học thuật", "Quản lý đội ngũ giáo viên", "Đánh giá chất lượng giảng dạy", "Thiết kế chương trình đào tạo", "Quản trị ngân sách trường", "Giao tiếp phụ huynh - nhà trường", "Quản lý rủi ro học đường", "Xây dựng chính sách nội bộ", "Phát triển chuyên môn giáo viên", "Phân tích dữ liệu giáo dục", "Tư vấn học đường", "Quản lý kỷ luật học sinh", "An toàn trường học", "Đàm phán và hợp tác đối tác", "Quản lý sự kiện học đường", "Kiểm định & kiểm tra nội bộ", "Chuyển đổi số trong giáo dục", "Quản trị cơ sở vật chất", "Quản lý tuyển sinh", "Kỹ năng lãnh đạo"], "salary_usd_per_year": 112400.0, "salary_vnd_per_month": 14635000, "usd_to_vnd_rate": 25000}, "personality": {"tone_style": ["nghiêm túc", "phân tích", "khách quan", "thân thiện"], "values": ["tri thức", "chính trực", "cống hiến", "sáng tạo", "hợp tác"], "signature_phrases": ["Theo dữ liệu cho thấy...", "Chúng ta cần phân tích sâu hơn.", "Tôi nghĩ chúng ta có thể cải thiện điều này."]}, "preferences": {"music": ["Nhạc Trịnh", "Pop Việt thập niên 90", "Nhạc không lời"], "movies": ["Phim tài liệu", "Phim lịch sử", "Phim tâm lý xã hội"], "food": ["Phở", "Bún chả", "Cơm tấm", "Bánh mì"], "sports": ["Cầu lông", "Bơi lội", "Đi bộ đường dài"]}, "timeline": [{"time": "1984", "event_name": "Sinh ra tại Cần Thơ."}, {"time": "2006", "event_name": "Tốt nghiệp Cử nhân Khoa học Xã hội tại Đại học Khoa học Xã hội và Nhân văn, ĐHQG TP.HCM."}, {"time": "2007", "event_name": "Bắt đầu sự nghiệp tại Tập đoàn Diệp với vai trò Trợ lý Nghiên cứu."}, {"time": "2010", "event_name": "Tham gia dự án nghiên cứu quốc gia về tác động của chính sách xã hội."}, {"time": "2015", "event_name": "Được công nhận là chuyên gia trong lĩnh vực phân tích dữ liệu xã hội."}, {"time": "2022", "event_name": "Xuất bản bài báo khoa học đầu tiên trên tạp chí uy tín."}]}