{"persona_id": "a53a54be-6dcd-43ea-beab-9b4e09c8d77e", "locale": "vi_VN", "timezone": "Asia/Ho_Chi_Minh", "name_full": "Nguyễn Vi Hiệp", "dob": "1982-5-31", "gender": "male", "nationality": "Viet Nam", "languages": [{"code": "vi", "level": "native"}, {"code": "en", "level": "intermediate"}], "location_region": "949 Phố Cam Canh Đình, Xã 6, Quận Diệp Thục Hà Giang", "appearance": {"height_cm": 180.3, "weight_kg": 75.7, "hair_color": "Green", "eye_color": "Green"}, "contacts": {"phone": "0169 474 6153", "email": "wngan@gmail.com", "website": "ung.com", "username": "dai.hinh"}, "work_education": {"job_title": "Kỹ thuật viên sửa chữa thân vỏ ô tô", "employer": "Công ty TNHH Dịch vụ Ô tô Lý Nhậm Sơn", "education": {"level": "Đại học", "university": "Đại học Bách khoa Hà Nội"}, "skills": ["Sửa chữa thân vỏ xe", "Hàn kim loại", "Sơn ô tô", "Gò, nắn khung xe", "Kiểm tra hư hỏng", "Sử dụng dụng cụ chuyên dụng", "Đọc bản vẽ kỹ thuật", "Lắp ráp phụ tùng", "Kiến thức về vật liệu ô tô", "An toàn lao động", "Chẩn đoán lỗi", "Bảo dưỡng ô tô", "Làm việc nhóm", "Giải quyết vấn đề", "Giao tiếp khách hàng", "Quản lý thời gian", "Kiểm soát chất lượng", "Sử dụng phần mềm chẩn đoán", "Kỹ năng cơ khí", "Đánh bóng xe"], "salary_usd_per_year": 89500.0, "salary_vnd_per_month": 11653000, "usd_to_vnd_rate": 25000}, "personality": {"tone_style": ["thực tế", "trung thực", "chuyên nghiệp", "thân thiện"], "values": ["chất lượng công việc", "trách nhiệm", "sự tỉ mỉ", "gia đình"], "signature_phrases": ["Cứ để tôi lo!", "Quan trọng là chất lượng.", "Không có gì là không sửa được."]}, "preferences": {"music": ["Tình thôi xót xa", "Giấc mơ có thật", "Em của ngày hôm qua"], "movies": ["Fast & Furious", "Người phán xử", "Bụi đời Chợ Lớn"], "food": ["Phở bò", "Bún chả", "Cơm tấm"], "sports": ["Bóng đá", "Cầu lông", "Bơi lội"]}, "timeline": [{"time": "1982", "event_name": "Sinh ra tại Hà Giang"}, {"time": "1988", "event_name": "Bắt đầu đi học tiểu học"}, {"time": "2000", "event_name": "Tốt nghiệp THPT"}, {"time": "2004", "event_name": "Tốt nghiệp Đại học Bách khoa Hà Nội, chuyên ngành Kỹ thuật Ô tô"}, {"time": "2005", "event_name": "Bắt đầu công việc Kỹ thuật viên sửa chữa thân vỏ ô tô tại Công ty TNHH Dịch vụ Ô tô Lý Nhậm Sơn"}, {"time": "2010", "event_name": "Kết hôn"}, {"time": "2012", "event_name": "Đón con đầu lòng"}, {"time": "2018", "event_name": "Được thăng chức Trưởng nhóm Kỹ thuật"}]}