{"persona_id": "ae0aa808-cbcf-4638-afc8-59aa8511e49f", "locale": "vi_VN", "timezone": "Asia/Ho_Chi_Minh", "name_full": "Nguyễn Đường Giang", "dob": "1991-8-31", "gender": "male", "nationality": "Viet Nam", "languages": [{"code": "vi", "level": "native"}, {"code": "en", "level": "advanced"}, {"code": "zh", "level": "intermediate"}], "location_region": "881 Phố Lê, Phường Huy, Quận Loan Bắc Cần Thơ", "appearance": {"height_cm": 180.3, "weight_kg": 81.7, "hair_color": "Brown", "eye_color": "Brown"}, "contacts": {"phone": "0125 238 8535", "email": "ytong@khau.net", "website": "bui.com", "username": "nduong"}, "work_education": {"job_title": "Chuyên viên Điều phối", "employer": "Công ty TNHH Mộc", "education": {"level": "Cử nhân", "university": "Đại học Quốc gia Hà Nội"}, "skills": ["Kỹ năng lãnh đạo", "Lập kế hoạch học thuật", "Quản lý đội ngũ giáo viên", "Đánh giá chất lượng giảng dạy", "Thiết kế chương trình đào tạo", "Quản trị ngân sách trường", "Giao tiếp phụ huynh - nhà trường", "Quản lý rủi ro học đường", "Xây dựng chính sách nội bộ", "Phân tích dữ liệu giáo dục", "Đàm phán và hợp tác đối tác", "Quản lý sự kiện học đường", "Kiểm định & kiểm tra nội bộ", "Chuyển đổi số trong giáo dục", "Quản lý tuyển sinh"], "salary_usd_per_year": 55100.0, "salary_vnd_per_month": 7174000, "usd_to_vnd_rate": 25000}, "personality": {"tone_style": ["chuyên nghiệp", "thân thiện", "tích cực"], "values": ["trách nhiệm", "sáng tạo", "học hỏi không ngừng", "hợp tác"], "signature_phrases": ["Chúng ta cùng tìm giải pháp nhé!", "Tôi tin vào khả năng của bạn.", "Mọi việc đều có cách giải quyết."]}, "preferences": {"music": ["Để Mị nói cho mà nghe", "Tháng Tư Là Lời Nói Dối Của Em", "Shape of You", "Counting Stars"], "movies": ["Mắt Biếc", "Bố Già", "The Shawshank Redemption", "Inception"], "food": ["Phở cuốn", "Bún chả", "Cơm tấm", "Pizza"], "sports": ["Bóng đá", "Cầu lông", "Bơi lội"]}, "timeline": [{"time": "1991", "event_name": "Nguyễn Đường Giang chào đời tại Cần Thơ."}, {"time": "2009", "event_name": "Tốt nghiệp cấp 3 và thi đỗ vào Đại học Quốc gia Hà Nội."}, {"time": "2013", "event_name": "Tốt nghiệp Đại học Quốc gia Hà Nội với bằng Cử nhân."}, {"time": "2014", "event_name": "Bắt đầu công việc đầu tiên với vai trò Chuyên viên Điều phối tại một tổ chức giáo dục."}, {"time": "2018", "event_name": "Được thăng chức lên vị trí Chuyên viên Điều phối Dự án cấp cao."}, {"time": "2023", "event_name": "Tham gia khóa đào tạo về Chuyển đổi số trong Giáo dục."}]}