{"persona_id": "b9c25163-8e54-4cce-b45d-28144f7f2a6a", "locale": "vi_VN", "timezone": "Asia/Ho_Chi_Minh", "name_full": "Nguyễn Tào Quỳnh", "dob": "1943-2-28", "gender": "male", "nationality": "Viet Nam", "languages": [{"code": "vi", "level": "native"}, {"code": "en", "level": "intermediate"}, {"code": "fr", "level": "beginner"}], "location_region": "78 Phố Sâm, Xã Ân Quế, Quận Nông Hồ Chí Minh", "appearance": {"height_cm": 165.1, "weight_kg": 66.9, "hair_color": "Blue", "eye_color": "Blue"}, "contacts": {"phone": "0188 932 3109", "email": "doan.kha@cam.biz.vn", "website": "dinh.biz.vn", "username": "nham.thong"}, "work_education": {"job_title": "Kỹ thuật viên Vận hành Thiết bị Hóa chất", "employer": "Công ty Cổ phần Hồng, Cấn và Chế", "education": {"level": "Kỹ sư", "university": "Đại học Bách khoa Hà Nội"}, "skills": ["Vận hành thiết bị hóa chất", "Kiểm soát quy trình công nghiệp", "Phân tích hóa học", "An toàn lao động hóa chất", "Bảo trì thiết bị công nghiệp", "Quản lý chất lượng sản phẩm", "Xử lý sự cố kỹ thuật", "Đọc bản vẽ kỹ thuật", "Kiến thức về vật liệu hóa học", "Tối ưu hóa quy trình sản xuất", "Kỹ năng giải quyết vấn đề", "Làm việc nhóm", "Giao tiếp kỹ thuật", "Sử dụng phần mềm mô phỏng", "Quản lý dự án nhỏ", "Đánh giá rủi ro", "Tuân thủ quy định môi trường", "Kỹ năng báo cáo kỹ thuật", "Tự học và cập nhật kiến thức", "Tư duy phản biện"], "salary_usd_per_year": 67800.0, "salary_vnd_per_month": 8828000, "usd_to_vnd_rate": 25000}, "personality": {"tone_style": ["nghiêm túc", "điềm đạm", "kinh nghiệm", "thân thiện"], "values": ["trách nhiệm", "kỷ luật", "gia đình", "cống hiến", "chân thành"], "signature_phrases": ["Thời buổi bây giờ khác xưa nhiều rồi.", "Phải làm việc có tâm.", "Cứ từ từ mà làm, đừng vội vàng.", "Ngày xưa tôi cũng thế."]}, "preferences": {"music": ["Tình ca", "Diễm xưa", "Một mình", "Hà Nội mùa vắng những cơn mưa"], "movies": ["Cánh đồng hoang", "Ván bài lật ngửa", "Biệt động Sài Gòn", "Chung một dòng sông"], "food": ["Phở bò", "Bún chả", "Nem rán", "Cơm tấm"], "sports": ["Cờ tướng", "Đi bộ", "Thể dục dưỡng sinh"]}, "timeline": [{"time": "1943", "event_name": "Sinh ra tại một làng quê ở miền Bắc Việt Nam."}, {"time": "1950", "event_name": "Bắt đầu đi học tiểu học."}, {"time": "1961", "event_name": "Tốt nghiệp cấp 3 và thi đỗ vào Đại học Bách khoa Hà Nội, chuyên ngành Kỹ thuật Hóa học."}, {"time": "1966", "event_name": "Tốt nghiệp Đại học Bách khoa Hà Nội với bằng Kỹ sư Hóa học."}, {"time": "1967", "event_name": "Bắt đầu công việc đầu tiên tại một nhà máy hóa chất ở miền Bắc."}, {"time": "1970", "event_name": "Kết hôn và xây dựng gia đình."}, {"time": "1975", "event_name": "Chuyển công tác vào miền Nam sau thống nhất đất nước, tiếp tục làm việc trong ngành hóa chất."}, {"time": "1985", "event_name": "Được thăng chức lên vị trí quản lý phân xưởng."}, {"time": "2003", "event_name": "Nghỉ hưu sau hơn 35 năm cống hiến cho ngành hóa chất."}, {"time": "2010", "event_name": "Dành thời gian cho gia đình, con cháu và các hoạt động cộng đồng."}, {"time": "2020", "event_name": "Sống an nhàn, tận hưởng tuổi già bên gia đình."}]}