{"persona_id": "bb196a9f-305d-473e-99f7-569b334f8622", "locale": "vi_VN", "timezone": "Asia/Ho_Chi_Minh", "name_full": "Uông Đồng Mẫn", "dob": "1994-2-28", "gender": "male", "nationality": "Viet Nam", "languages": [{"code": "vi", "level": "native"}, {"code": "en", "level": "advanced"}, {"code": "ja", "level": "intermediate"}], "location_region": "8405 Phố Tuyền, Xã 84, Huyện Trâm Thương Đà Nẵng", "appearance": {"height_cm": 167.6, "weight_kg": 71.0, "hair_color": "Green", "eye_color": "Green"}, "contacts": {"phone": "0350 138 0528", "email": "ynguy@la.net.vn", "website": "ha.net.vn", "username": "slu"}, "work_education": {"job_title": "Quản lý Tài chính", "employer": "Tập đoàn Tài chính Mang & Con", "education": {"level": "Cử nhân", "university": "Đại học Kinh tế Quốc dân"}, "skills": ["Phân tích tài chính", "Quản lý ngân sách", "Đầu tư", "Kế toán", "Thẩm định dự án", "Quản lý rủi ro tài chính", "Lập kế hoạch tài chính", "Phân tích thị trường", "Đàm phán", "Kỹ năng lãnh đạo", "Giải quyết vấn đề", "Giao tiếp hiệu quả", "Sử dụng phần mềm tài chính", "Excel nâng cao", "Báo cáo tài chính", "Tuân thủ quy định pháp luật", "Quản lý dòng tiền", "Phân tích dữ liệu", "Tư vấn tài chính", "Xây dựng chiến lược kinh doanh"], "salary_usd_per_year": 93200.0, "salary_vnd_per_month": 12135000, "usd_to_vnd_rate": 25000}, "personality": {"tone_style": ["nghiêm túc", "chuyên nghiệp", "thẳng thắn", "có trách nhiệm"], "values": ["hiệu quả", "minh bạch", "phát triển bền vững", "gia đình"], "signature_phrases": ["Chúng ta cần xem xét kỹ lưỡng", "Dữ liệu cho thấy...", "Hãy tối ưu hóa nguồn lực"]}, "preferences": {"music": ["Em của ngày hôm qua", "Lạc trôi", "Nơi này có anh", "Đường đến ngày vinh quang"], "movies": ["Bố già", "Hai Phượng", "Avengers: Endgame", "The Shawshank Redemption"], "food": ["Phở bò", "Bún chả", "Cơm tấm", "Hải sản nướng"], "sports": ["Bóng đá", "Cầu lông", "Bơi lội"]}, "timeline": [{"time": "1994", "event_name": "Sinh ra tại Đà Nẵng"}, {"time": "2000", "event_name": "Bắt đầu đi học tiểu học"}, {"time": "2012", "event_name": "Tốt nghiệp THPT và thi đỗ Đại học Kinh tế Quốc dân"}, {"time": "2016", "event_name": "Tốt nghiệp Đại học Kinh tế Quốc dân với bằng Cử nhân Tài chính"}, {"time": "2016", "event_name": "Bắt đầu công việc đầu tiên tại một công ty tài chính"}, {"time": "2020", "event_name": "Thăng chức lên vị trí Quản lý Tài chính tại Tập đoàn Tài chính Mang & Con"}, {"time": "2022", "event_name": "Kết hôn"}]}