{"persona_id": "d9b4d0a3-b6f4-41ad-93e9-05bb75474f2d", "locale": "vi_VN", "timezone": "Asia/Ho_Chi_Minh", "name_full": "Nguyễn Khuất Tuyết", "dob": "1948-6-30", "gender": "female", "nationality": "Viet Nam", "languages": [{"code": "vi", "level": "native"}, {"code": "en", "level": "intermediate"}, {"code": "ru", "level": "beginner"}], "location_region": "72 Phố Kỳ, Xã 49, Quận Bạch Sáng Sóc Trăng", "appearance": {"height_cm": 165.1, "weight_kg": 53.6, "hair_color": "Brown", "eye_color": "Brown"}, "contacts": {"phone": "(0162) 193 0275", "email": "due73@hotmail.com", "website": "thoi.com", "username": "chuong77"}, "work_education": {"job_title": "Giảng viên cao cấp", "employer": "Trường Đại học Sư phạm Hà Nội", "education": {"level": "Cử nhân", "university": "Đại học Sư phạm Hà Nội"}, "skills": ["Nghiên cứu khoa học", "Giảng dạy đại học", "Phát triển chương trình học", "Hướng dẫn sinh viên", "Đánh giá kết quả học tập", "Viết báo khoa học", "Tham gia hội thảo chuyên ngành", "Quản lý dự án nghiên cứu", "Tư vấn học thuật", "Kỹ năng thuyết trình", "Giao tiếp hiệu quả", "Làm việc nhóm", "Giải quyết vấn đề", "Tư duy phản biện", "Sử dụng công nghệ trong giảng dạy", "Quản lý thời gian", "Đạo đức nghề nghiệp", "Xây dựng mối quan hệ", "Phân tích dữ liệu", "Lãnh đạo nhóm nghiên cứu"], "salary_usd_per_year": 87800.0, "salary_vnd_per_month": 11432000, "usd_to_vnd_rate": 25000}, "personality": {"tone_style": ["nghiêm túc", "trang trọng", "tận tâm", "truyền cảm hứng"], "values": ["tri thức", "kỷ luật", "trách nhiệm", "gia đình", "cống hiến"], "signature_phrases": ["Các em phải cố gắng!", "Kiến thức là sức mạnh.", "Hãy luôn học hỏi."]}, "preferences": {"music": ["Tình ca", "Bài ca hy vọng", "Em ơi Hà Nội phố"], "movies": ["Vĩ tuyến 17 ngày và đêm", "Chị Dậu", "Cánh đồng hoang"], "food": ["Phở", "Bún chả", "Nem rán", "Canh cua"], "sports": ["Đi bộ", "Thể dục dưỡng sinh", "Xem bóng đá"]}, "timeline": [{"time": "1948", "event_name": "Sinh ra tại Sóc Trăng."}, {"time": "1954", "event_name": "Gia đình di cư ra Bắc sau Hiệp định Genève."}, {"time": "1966", "event_name": "Tốt nghiệp cấp 3, thi đỗ vào Đại học Sư phạm Hà Nội."}, {"time": "1970", "event_name": "Tốt nghiệp Đại học Sư phạm Hà Nội, bắt đầu sự nghiệp giảng dạy."}, {"time": "1985", "event_name": "Hoàn thành chương trình Thạc sĩ, trở thành Giảng viên chính."}, {"time": "1998", "event_name": "Được phong tặng danh hiệu \"Nhà giáo Ưu tú\"."}, {"time": "2008", "event_name": "Về hưu, tiếp tục tham gia các hoạt động tư vấn giáo dục."}]}