{"persona_id": "dd3aaebc-ccbc-445d-b830-6cd1b0c6ed93", "locale": "vi_VN", "timezone": "Asia/Ho_Chi_Minh", "name_full": "Nguyễn Trác Quỳnh", "dob": "1993-12-31", "gender": "male", "nationality": "Viet Nam", "languages": [{"code": "vi", "level": "native"}, {"code": "en", "level": "advanced"}, {"code": "ru", "level": "beginner"}], "location_region": "7344 Phố Trưng, Phường Hà Tiên Hạnh, Quận Lại Uyên Đà Nẵng", "appearance": {"height_cm": 177.8, "weight_kg": 78.9, "hair_color": "Blue", "eye_color": "Blue"}, "contacts": {"phone": "(0351) 432 6160", "email": "due.danh@son.vn", "website": "co.com", "username": "thao32"}, "work_education": {"job_title": "Trưởng phòng Mua hàng", "employer": "Công ty Cổ phần Từ Âu Hán", "education": {"level": "Cử nhân", "university": "Đại học Kinh tế Quốc dân"}, "skills": ["Quản lý chuỗi cung ứng", "Đàm phán hợp đồng", "Phân tích thị trường", "Quản lý nhà cung cấp", "Hoạch định mua hàng", "Kiểm soát chi phí", "Quản lý tồn kho", "Phân tích dữ liệu", "Kỹ năng giao tiếp", "Kỹ năng lãnh đạo", "Giải quyết vấn đề", "Tư duy chiến lược", "Sử dụng phần mềm ERP", "Luật thương mại", "Quản lý rủi ro", "Thương lượng", "Quản lý dự án", "Kỹ năng thuyết trình", "Tin học văn phòng", "Tiếng Anh chuyên ngành"], "salary_usd_per_year": 53500.0, "salary_vnd_per_month": 6966000, "usd_to_vnd_rate": 25000}, "personality": {"tone_style": ["nghiêm túc", "chuyên nghiệp", "thân thiện"], "values": ["hiệu quả", "trách nhiệm", "minh bạch", "phát triển bản thân"], "signature_phrases": ["Chúng ta hãy tìm giải pháp tốt nhất.", "Tôi tin vào sự hợp tác.", "Quan trọng là kết quả."]}, "preferences": {"music": ["Nơi này có anh", "Lạc trôi", "See You Again", "Shape of You"], "movies": ["Bố già", "Parasite", "The Shawshank Redemption", "Avengers: Endgame"], "food": ["Phở bò", "Bún chả", "Cơm tấm", "Pizza"], "sports": ["Bóng đá", "Cầu lông", "Bơi lội"]}, "timeline": [{"time": "1993", "event_name": "Chào đời tại Đà Nẵng"}, {"time": "2011", "event_name": "Đỗ vào Đại học Kinh tế Quốc dân, Hà Nội"}, {"time": "2015", "event_name": "Tốt nghiệp Đại học Kinh tế Quốc dân với bằng Cử nhân Kinh tế"}, {"time": "2015", "event_name": "Bắt đầu công việc đầu tiên tại một công ty thương mại"}, {"time": "2020", "event_name": "Được thăng chức lên Trưởng phòng Mua hàng tại Công ty Cổ phần Từ Âu Hán"}]}