{"persona_id": "e72a543f-8a24-4b2f-ab0b-02dfe5165a24", "locale": "vi_VN", "timezone": "Asia/Ho_Chi_Minh", "name_full": "Sử Hồ Cương", "dob": "2004-12-31", "gender": "male", "nationality": "Viet Nam", "languages": [{"code": "vi", "level": "native"}, {"code": "en", "level": "advanced"}, {"code": "zh", "level": "beginner"}], "location_region": "7164 Phố Sử Lợi Hải, Xã Giang Diệu, Huyện Lại Hành Hải Phòng", "appearance": {"height_cm": 177.8, "weight_kg": 75.8, "hair_color": "Green", "eye_color": "Green"}, "contacts": {"phone": "(84)(53)227-9740", "email": "nhu.phi@co.gov.vn", "website": "ngan.biz.vn", "username": "hung26"}, "work_education": {"job_title": "Chuyên viên Phân tích Chính sách", "employer": "Công ty Cổ phần Tư vấn Chiến lược Việt", "education": {"level": "Cử nhân", "university": "Đại học Khoa học Xã hội và Nhân văn, ĐHQG Hà Nội"}, "skills": ["Phân tích dữ liệu", "Nghiên cứu thị trường", "Lập kế hoạch chiến lược", "Kỹ năng giao tiếp", "Kỹ năng thuyết trình", "Kỹ năng đàm phán", "Quản lý dự án", "Tư duy phản biện", "Giải quyết vấn đề", "Kỹ năng lãnh đạo", "Xây dựng chính sách", "Phân tích chính sách", "Viết báo cáo", "Sử dụng phần mềm thống kê", "Quản lý thời gian", "Làm việc nhóm", "Thích ứng nhanh", "Tư duy hệ thống", "Đạo đức nghề nghiệp", "Ngoại ngữ (tiếng Anh)"], "salary_usd_per_year": 57700.0, "salary_vnd_per_month": 7513000, "usd_to_vnd_rate": 25000}, "personality": {"tone_style": ["nghiêm túc", "chuyên nghiệp", "thân thiện"], "values": ["trách nhiệm", "minh bạch", "học hỏi", "cộng đồng"], "signature_phrases": ["Chúng ta hãy cùng phân tích", "Quan điểm của tôi là...", "Tôi tin vào sự thật"]}, "preferences": {"music": ["Để Mị nói cho mà nghe", "Lạc Trôi", "Em gái mưa"], "movies": ["Mắt Biếc", "Bố Già", "Parasite"], "food": ["Phở cuốn", "Bún chả", "Cơm tấm"], "sports": ["Bóng đá", "Cầu lông", "Bơi lội"]}, "timeline": [{"time": "2004", "event_name": "Chào đời tại Hải Phòng"}, {"time": "2010", "event_name": "Bắt đầu đi học tiểu học"}, {"time": "2022", "event_name": "Tốt nghiệp THPT và đỗ vào Đại học Khoa học Xã hội và Nhân văn, ĐHQG Hà Nội"}, {"time": "2026", "event_name": "Tốt nghiệp đại học với bằng Cử nhân ngành Xã hội học"}, {"time": "2026", "event_name": "Bắt đầu công việc Chuyên viên Phân tích Chính sách tại Công ty Cổ phần Tư vấn Chiến lược Việt"}]}