{"persona_id": "fa40082a-1241-4e28-aaca-06ebf77d2495", "locale": "vi_VN", "timezone": "Asia/Ho_Chi_Minh", "name_full": "Tòng Hướng Bạch", "dob": "2002-1-31", "gender": "male", "nationality": "Viet Nam", "languages": [{"code": "vi", "level": "native"}, {"code": "en", "level": "advanced"}], "location_region": "571 Phố Tống Khanh Uy, Phường Cổ Ly Vỹ, Quận 6 Trà Vinh", "appearance": {"height_cm": 190.5, "weight_kg": 85.0, "hair_color": "Brown", "eye_color": "Brown"}, "contacts": {"phone": "079 708 1539", "email": "ptrang@gmail.com", "website": "tra.biz.vn", "username": "udoi"}, "work_education": {"job_title": "Quản lý sản xuất công nghiệp", "employer": "Hùng-Tăng Tập đoàn", "education": {"level": "Kỹ sư", "university": "Đại học Bách khoa Hà Nội"}, "skills": ["Quản lý dự án", "Tối ưu hóa quy trình sản xuất", "Kiểm soát chất lượng", "Phân tích dữ liệu sản xuất", "Quản lý chuỗi cung ứng", "Tự động hóa công nghiệp", "Bảo trì công nghiệp", "An toàn lao động", "Thiết kế sản phẩm", "Vật liệu học", "Cơ khí chế tạo", "Điện tử công nghiệp", "Lập trình PLC", "Hệ thống ERP", "Lean Manufacturing", "Six Sigma", "Giải quyết vấn đề", "Lãnh đạo nhóm", "Giao tiếp kỹ thuật", "Đàm phán"], "salary_usd_per_year": 87500.0, "salary_vnd_per_month": 11393000, "usd_to_vnd_rate": 25000}, "personality": {"tone_style": ["nghiêm túc", "thực tế", "quyết đoán"], "values": ["hiệu quả", "kỷ luật", "chất lượng", "đổi mới"], "signature_phrases": ["Cần phải tối ưu hóa quy trình này.", "Chất lượng là ưu tiên hàng đầu.", "Hãy tìm giải pháp hiệu quả nhất."]}, "preferences": {"music": ["Em của ngày hôm qua", "Lạc trôi", "Nơi này có anh"], "movies": ["Bố già", "Hai Phượng", "Fast & Furious"], "food": ["Phở bò", "Bún chả", "Cơm tấm"], "sports": ["Bóng đá", "Cầu lông", "Bơi lội"]}, "timeline": [{"time": "2002", "event_name": "Sinh ra"}, {"time": "2020", "event_name": "Tốt nghiệp THPT"}, {"time": "2020", "event_name": "Bắt đầu học Đại học Bách khoa Hà Nội"}, {"time": "2024", "event_name": "Tốt nghiệp Đại học Bách khoa Hà Nội"}, {"time": "2024", "event_name": "Bắt đầu làm việc tại Hùng-Tăng Group với vai trò Quản lý sản xuất công nghiệp"}]}